haven/__init__.py
haven/haven_chk.py
haven/haven_img.py
haven/haven_utils.py
haven/haven_wizard.py
haven/haven_jobs/__init__.py
haven/haven_jobs/slurm_manager.py
haven/haven_jobs/toolkit_manager.py
haven/haven_jupyter/__init__.py
haven/haven_jupyter/images_tab.py
haven/haven_jupyter/latex_tab.py
haven/haven_jupyter/plots_tab.py
haven/haven_jupyter/share_tab.py
haven/haven_jupyter/tables_tab.py
haven/haven_jupyter/text_tab.py
haven/haven_jupyter/widgets.py
haven/haven_jupyter_deprecated/__init__.py
haven/haven_jupyter_deprecated/images_tab.py
haven/haven_jupyter_deprecated/latex_tab.py
haven/haven_jupyter_deprecated/plots_tab.py
haven/haven_jupyter_deprecated/share_tab.py
haven/haven_jupyter_deprecated/tables_tab.py
haven/haven_jupyter_deprecated/text_tab.py
haven/haven_jupyter_deprecated/widgets.py
haven/haven_results/__init__.py
haven/haven_results/images_fig.py
haven/haven_results/latex_tables.py
haven/haven_results/plots_bar.py
haven/haven_results/plots_line.py
haven/haven_results/pretty_plot.py
haven/haven_results/tables_scores.py
haven/haven_share/__init__.py
haven/haven_share/dropbox_share.py
haven/haven_share/gdrive_share.py
scripts/__init__.py
scripts/command_line.py
scripts/gdown_script.py
scripts/generate_report.py
scripts/test_best_model.py
scripts/test_example.py
scripts/test_latex.py
scripts/test_slurm.py
scripts/test_wandb.py
haven_ai-0.7.3.dist-info/LICENSE
haven_ai-0.7.3.dist-info/METADATA
haven_ai-0.7.3.dist-info/WHEEL
haven_ai-0.7.3.dist-info/top_level.txt
haven_ai-0.7.3.dist-info/RECORD
