Metadata-Version: 2.1
Name: haven-ai
Version: 0.7.3
Summary: Manage large-scale experiments
Home-page: https://github.com/haven-ai/haven-ai
Maintainer: Issam Laradji
Maintainer-email: issam.laradji@gmail.com
License: MIT
Platform: UNKNOWN
Requires-Python: >=3.5
License-File: LICENSE
Requires-Dist: requests (>=0.0)
Requires-Dist: tqdm (>=0.0)
Requires-Dist: matplotlib (>=0.0)
Requires-Dist: numpy (>=0.0)
Requires-Dist: pandas (>=0.0)
Requires-Dist: notebook (>=4.0)
